polars_fastavro/__init__.py
polars_fastavro/_scan.py
polars_fastavro/_sink.py
polars_fastavro/py.typed
polars_fastavro-0.5.1.dist-info/METADATA
polars_fastavro-0.5.1.dist-info/WHEEL
polars_fastavro-0.5.1.dist-info/licenses/LICENSE
polars_fastavro-0.5.1.dist-info/RECORD
