Metadata-Version: 2.4
Name: polars-fastavro
Version: 0.5.1
Summary: A polars io-plugin wrapper around fastavro
License-File: LICENSE
Requires-Python: >=3.10
Requires-Dist: fastavro>=1.9.0
Requires-Dist: polars>=1.3.0
